[{"id":1,"title":"Campus Tours","description":"","event_cover":null,"category_id":null,"creator_id":null,"created_at":"2016-09-05 23:18:08","updated_at":"2016-09-05 23:18:09","deleted_at":null,"date_start":"2016-09-15","date_end":null,"time_start":"11:00am","time_end":"5:00pm","price":"Free","location_address":"Students' Union","location_name":"Students' Union foyer","tickets_link":"","featured":0,"subtitle":"","society_id":null,"lat":"53.464363","lng":"-2.2323628","cover":"covers\/University.Tours.1600x900.jpg","slug":"campus-tours-2016-09-15-1100am"},{"id":2,"title":"Film At 5: Kingsman: The Secret Service","description":"","event_cover":null,"category_id":null,"creator_id":null,"created_at":"2016-09-05 23:18:09","updated_at":"2016-09-05 23:18:10","deleted_at":null,"date_start":"2016-09-15","date_end":null,"time_start":"5:00pm","time_end":"until finished","price":"Free","location_address":"Students' Union","location_name":"Council Chambers, Students' Union","tickets_link":"","featured":0,"subtitle":"","society_id":null,"lat":"53.464363","lng":"-2.2323628","cover":"covers\/Kingsman.1600x900.jpg","slug":"film-at-5-kingsman-the-secret-service-2016-09-15-500pm"},{"id":3,"title":"Conversation Corner: International Students","description":"","event_cover":null,"category_id":null,"creator_id":null,"created_at":"2016-09-05 23:18:10","updated_at":"2016-09-05 23:18:10","deleted_at":null,"date_start":"2016-09-15","date_end":null,"time_start":"5:00pm","time_end":"6:30pm","price":"Free","location_address":"Manchester Academy","location_name":"Academy 2, Students' Union","tickets_link":"","featured":0,"subtitle":"","society_id":null,"lat":"53.4635701","lng":"-2.2315516","cover":"covers\/CC16.Weblistings.Int.16x9.jpg","slug":"conversation-corner-international-students-2016-09-15-500pm"},{"id":4,"title":"Activities At The Union","description":"","event_cover":null,"category_id":null,"creator_id":null,"created_at":"2016-09-05 23:18:10","updated_at":"2016-09-05 23:18:11","deleted_at":null,"date_start":"2016-09-15","date_end":null,"time_start":"6:30pm","time_end":"8:30pm","price":"Free","location_address":"Manchester Academy","location_name":"Academy 2, Students' Union","tickets_link":"","featured":0,"subtitle":"","society_id":null,"lat":"53.4635701","lng":"-2.2315516","cover":"covers\/Union.Activities.1600x900.jpg","slug":"activities-at-the-union-2016-09-15-630pm"},{"id":5,"title":"Campus Tours","description":"","event_cover":null,"category_id":null,"creator_id":null,"created_at":"2016-09-05 23:18:11","updated_at":"2016-09-05 23:18:11","deleted_at":null,"date_start":"2016-09-16","date_end":null,"time_start":"11:00am","time_end":"5:00pm","price":"Free","location_address":"Students' Union","location_name":"Students' Union foyer","tickets_link":"","featured":0,"subtitle":"","society_id":null,"lat":"53.464363","lng":"-2.2323628","cover":"covers\/University.Tours.1600x900.jpg","slug":"campus-tours-2016-09-16-1100am"},{"id":6,"title":"Film At 5: Frozen","description":"","event_cover":null,"category_id":null,"creator_id":null,"created_at":"2016-09-05 23:18:11","updated_at":"2016-09-05 23:18:12","deleted_at":null,"date_start":"2016-09-16","date_end":null,"time_start":"5:00pm","time_end":"until finished","price":"Free","location_address":"Students' Union","location_name":"Council Chambers, Students' Union","tickets_link":"","featured":0,"subtitle":"","society_id":null,"lat":"53.464363","lng":"-2.2323628","cover":"covers\/Frozen.1600x900.jpg","slug":"film-at-5-frozen-2016-09-16-500pm"},{"id":7,"title":"World Quiz","description":"","event_cover":null,"category_id":null,"creator_id":null,"created_at":"2016-09-05 23:18:12","updated_at":"2016-09-05 23:18:12","deleted_at":null,"date_start":"2016-09-16","date_end":null,"time_start":"7:00pm","time_end":"9:00pm","price":"Free","location_address":"Students' Union","location_name":"Club Academy, Students' Union","tickets_link":"","featured":0,"subtitle":"","society_id":null,"lat":"53.464363","lng":"-2.2323628","cover":"covers\/Lets.Get.Quiz.1600x900.jpg","slug":"world-quiz-2016-09-16-700pm"},{"id":8,"title":"Campus Tours","description":"","event_cover":null,"category_id":null,"creator_id":null,"created_at":"2016-09-05 23:18:13","updated_at":"2016-09-05 23:18:13","deleted_at":null,"date_start":"2016-09-17","date_end":null,"time_start":"11:00am","time_end":"5:00pm","price":"Free","location_address":"Students' Union","location_name":"Students' Union foyer","tickets_link":"","featured":0,"subtitle":"","society_id":null,"lat":"53.464363","lng":"-2.2323628","cover":"covers\/University.Tours.1600x900.jpg","slug":"campus-tours-2016-09-17-1100am"},{"id":9,"title":"Film At 5: Spectre","description":"","event_cover":null,"category_id":null,"creator_id":null,"created_at":"2016-09-05 23:18:13","updated_at":"2016-09-05 23:18:14","deleted_at":null,"date_start":"2016-09-17","date_end":null,"time_start":"5:00pm","time_end":"until finished","price":"Free","location_address":"Students' Union","location_name":"Council Chambers, Students' Union","tickets_link":"","featured":0,"subtitle":"","society_id":null,"lat":"53.464363","lng":"-2.2323628","cover":"covers\/Spectre.1600x900.jpg","slug":"film-at-5-spectre-2016-09-17-500pm"},{"id":10,"title":"Mingle After Hours","description":"","event_cover":null,"category_id":null,"creator_id":null,"created_at":"2016-09-05 23:18:14","updated_at":"2016-09-05 23:18:15","deleted_at":null,"date_start":"2016-09-17","date_end":null,"time_start":"9:00pm","time_end":"2:00am","price":"Free","location_address":"Students' Union","location_name":"Union Bar, Students' Union","tickets_link":"","featured":0,"subtitle":"","society_id":null,"lat":"53.464363","lng":"-2.2323628","cover":"covers\/Mingle.AfterHours.1600x900.jpg","slug":"mingle-after-hours-2016-09-17-900pm"},{"id":11,"title":"Campus Tours","description":"","event_cover":null,"category_id":null,"creator_id":null,"created_at":"2016-09-05 23:18:15","updated_at":"2016-09-05 23:18:16","deleted_at":null,"date_start":"2016-09-18","date_end":null,"time_start":"11:00am","time_end":"5:00pm","price":"Free","location_address":"Students' Union","location_name":"Students' Union foyer","tickets_link":"","featured":0,"subtitle":"","society_id":null,"lat":"53.464363","lng":"-2.2323628","cover":"covers\/University.Tours.1600x900.jpg","slug":"campus-tours-2016-09-18-1100am"},{"id":12,"title":"Culture And Faith Fair","description":"","event_cover":null,"category_id":null,"creator_id":null,"created_at":"2016-09-05 23:18:16","updated_at":"2016-09-05 23:18:16","deleted_at":null,"date_start":"2016-09-18","date_end":null,"time_start":"2:00pm","time_end":"6:00pm","price":"Free","location_address":"Students' Union","location_name":"Academy 2, Students' Union","tickets_link":"","featured":0,"subtitle":"","society_id":null,"lat":"53.464363","lng":"-2.2323628","cover":"covers\/Culture.Faith.1600x900.jpg","slug":"culture-and-faith-fair-2016-09-18-200pm"},{"id":13,"title":"Film At 5: Back To The Future","description":"","event_cover":null,"category_id":null,"creator_id":null,"created_at":"2016-09-05 23:18:16","updated_at":"2016-09-05 23:18:17","deleted_at":null,"date_start":"2016-09-18","date_end":null,"time_start":"5:00pm","time_end":"until finished","price":"Free","location_address":"Students' Union","location_name":"Council Chambers, Students' Union","tickets_link":"","featured":0,"subtitle":"","society_id":null,"lat":"53.464363","lng":"-2.2323628","cover":"covers\/Back.to.The.Future.1600x900.jpg","slug":"film-at-5-back-to-the-future-2016-09-18-500pm"},{"id":14,"title":"Home Away From Home","description":"","event_cover":null,"category_id":null,"creator_id":null,"created_at":"2016-09-05 23:18:17","updated_at":"2016-09-05 23:18:17","deleted_at":null,"date_start":"2016-09-19","date_end":null,"time_start":"8:00am","time_end":"4:30pm","price":"Free","location_address":"Students' Union","location_name":"Room 8, Students\u2019 Union","tickets_link":"","featured":0,"subtitle":"","society_id":null,"lat":"53.464363","lng":"-2.2323628","cover":"covers\/Home.Away.From.Home.1600x900.jpg","slug":"home-away-from-home-2016-09-19-800am"},{"id":15,"title":"Campus Tours","description":"","event_cover":null,"category_id":null,"creator_id":null,"created_at":"2016-09-05 23:18:17","updated_at":"2016-09-05 23:18:18","deleted_at":null,"date_start":"2016-09-19","date_end":null,"time_start":"12:00pm","time_end":"3:00pm","price":"Free","location_address":"Students' Union","location_name":"Students' Union foyer","tickets_link":"","featured":0,"subtitle":"","society_id":null,"lat":"53.464363","lng":"-2.2323628","cover":"covers\/University.Tours.1600x900.jpg","slug":"campus-tours-2016-09-19-1200pm"},{"id":16,"title":"Film At 5: Labyrinth","description":"","event_cover":null,"category_id":null,"creator_id":null,"created_at":"2016-09-05 23:18:18","updated_at":"2016-09-05 23:18:18","deleted_at":null,"date_start":"2016-09-19","date_end":null,"time_start":"5:00pm","time_end":"until finished","price":"Free","location_address":"Students' Union","location_name":"Council Chambers, Students' Union","tickets_link":"","featured":0,"subtitle":"","society_id":null,"lat":"53.464363","lng":"-2.2323628","cover":"covers\/Labyrinth.1600x900.jpg","slug":"film-at-5-labyrinth-2016-09-19-500pm"},{"id":17,"title":"Conversation Corner: Black And Minority Ethnic Students","description":"","event_cover":null,"category_id":null,"creator_id":null,"created_at":"2016-09-05 23:18:18","updated_at":"2016-09-05 23:18:19","deleted_at":null,"date_start":"2016-09-19","date_end":null,"time_start":"5:00pm","time_end":"6:30pm","price":"Free","location_address":"Students' Union","location_name":"Room 8 ,Students' Union","tickets_link":"","featured":0,"subtitle":"","society_id":null,"lat":"53.464363","lng":"-2.2323628","cover":"covers\/CC16.Weblistings.Black.16x9.jpg","slug":"conversation-corner-black-and-minority-ethnic-students-2016-09-19-500pm"},{"id":18,"title":"Let's Get Quizzical","description":"","event_cover":null,"category_id":null,"creator_id":null,"created_at":"2016-09-05 23:18:19","updated_at":"2016-09-05 23:18:20","deleted_at":null,"date_start":"2016-09-19","date_end":null,"time_start":"6:00pm","time_end":"8:00pm","price":"Free","location_address":"Students' Union","location_name":"Union Bar, Students' Union","tickets_link":"","featured":0,"subtitle":"","society_id":null,"lat":"53.464363","lng":"-2.2323628","cover":"covers\/Lets.Get.Quiz.1600x900.jpg","slug":"lets-get-quizzical-2016-09-19-600pm"},{"id":19,"title":"Home Away From Home","description":"","event_cover":null,"category_id":null,"creator_id":null,"created_at":"2016-09-05 23:18:20","updated_at":"2016-09-05 23:18:20","deleted_at":null,"date_start":"2016-09-20","date_end":null,"time_start":"8:00am","time_end":"6:00pm","price":"Free","location_address":"Students' Union","location_name":"Room 8 ,Students' Union","tickets_link":"","featured":0,"subtitle":"","society_id":null,"lat":"53.464363","lng":"-2.2323628","cover":"covers\/Home.Away.From.Home.1600x900.jpg","slug":"home-away-from-home-2016-09-20-800am"},{"id":20,"title":"Welcome Fair","description":"","event_cover":null,"category_id":null,"creator_id":null,"created_at":"2016-09-05 23:18:20","updated_at":"2016-09-05 23:18:21","deleted_at":null,"date_start":"2016-09-20","date_end":null,"time_start":"10:00am","time_end":"4:00pm","price":"Free","location_address":"Students' Union","location_name":"Students' Union","tickets_link":"","featured":0,"subtitle":"","society_id":null,"lat":"53.464363","lng":"-2.2323628","cover":"covers\/Welcome.Fair.1600x900.jpg","slug":"welcome-fair-2016-09-20-1000am"},{"id":21,"title":"Campus Tours","description":"","event_cover":null,"category_id":null,"creator_id":null,"created_at":"2016-09-05 23:18:21","updated_at":"2016-09-05 23:18:21","deleted_at":null,"date_start":"2016-09-20","date_end":null,"time_start":"12:00pm","time_end":"3:00pm","price":"Free","location_address":"Students' Union","location_name":"Students' Union foyer","tickets_link":"","featured":0,"subtitle":"","society_id":null,"lat":"53.464363","lng":"-2.2323628","cover":"covers\/University.Tours.1600x900.jpg","slug":"campus-tours-2016-09-20-1200pm"},{"id":22,"title":"Film At 5: Hot Fuzz","description":"","event_cover":null,"category_id":null,"creator_id":null,"created_at":"2016-09-05 23:18:21","updated_at":"2016-09-05 23:18:22","deleted_at":null,"date_start":"2016-09-20","date_end":null,"time_start":"5:00pm","time_end":"until finished","price":"Free","location_address":"Manchester Academy","location_name":"Academy 3, Students' Union","tickets_link":"","featured":0,"subtitle":"","society_id":null,"lat":"53.4635701","lng":"-2.2315516","cover":"covers\/Hot.fuzz.1600x900.jpg","slug":"film-at-5-hot-fuzz-2016-09-20-500pm"},{"id":23,"title":"Conversation Corner: LGBTQ","description":"","event_cover":null,"category_id":null,"creator_id":null,"created_at":"2016-09-05 23:18:22","updated_at":"2016-09-05 23:18:23","deleted_at":null,"date_start":"2016-09-20","date_end":null,"time_start":"5:00pm","time_end":"6:30pm","price":"Free","location_address":"Students' Union","location_name":"Council Chambers, Students' Union","tickets_link":"","featured":0,"subtitle":"","society_id":null,"lat":"53.464363","lng":"-2.2323628","cover":"covers\/CC16.Weblistings.LGBT.16x9.jpg","slug":"conversation-corner-lgbtq-2016-09-20-500pm"},{"id":24,"title":"Home Away From Home","description":"","event_cover":null,"category_id":null,"creator_id":null,"created_at":"2016-09-05 23:18:23","updated_at":"2016-09-05 23:18:23","deleted_at":null,"date_start":"2016-09-21","date_end":null,"time_start":"8:00am","time_end":"12:30pm","price":"Free","location_address":"Students' Union","location_name":"Room 8 ,Students' Union","tickets_link":"","featured":0,"subtitle":"","society_id":null,"lat":"53.464363","lng":"-2.2323628","cover":"covers\/Home.Away.From.Home.1600x900.jpg","slug":"home-away-from-home-2016-09-21-800am"},{"id":25,"title":"Home Away From Home","description":"","event_cover":null,"category_id":null,"creator_id":null,"created_at":"2016-09-05 23:18:23","updated_at":"2016-09-05 23:18:24","deleted_at":null,"date_start":"2016-09-21","date_end":null,"time_start":"2:30pm","time_end":"6:00pm","price":"Free","location_address":"Students' Union","location_name":"Room 8 ,Students' Union","tickets_link":"","featured":0,"subtitle":"","society_id":null,"lat":"53.464363","lng":"-2.2323628","cover":"covers\/Home.Away.From.Home.1600x900.jpg","slug":"home-away-from-home-2016-09-21-230pm"},{"id":26,"title":"Welcome Fair","description":"","event_cover":null,"category_id":null,"creator_id":null,"created_at":"2016-09-05 23:18:24","updated_at":"2016-09-05 23:18:24","deleted_at":null,"date_start":"2016-09-21","date_end":null,"time_start":"10:00am","time_end":"4:00pm","price":"Free","location_address":"Students' Union","location_name":"Students' Union","tickets_link":"","featured":0,"subtitle":"","society_id":null,"lat":"53.464363","lng":"-2.2323628","cover":"covers\/Welcome.Fair.1600x900.jpg","slug":"welcome-fair-2016-09-21-1000am"},{"id":27,"title":"Campus Tours","description":"","event_cover":null,"category_id":null,"creator_id":null,"created_at":"2016-09-05 23:18:24","updated_at":"2016-09-05 23:18:25","deleted_at":null,"date_start":"2016-09-21","date_end":null,"time_start":"12:00pm","time_end":"3:00pm","price":"Free","location_address":"Students' Union","location_name":"Students' Union foyer","tickets_link":"","featured":0,"subtitle":"","society_id":null,"lat":"53.464363","lng":"-2.2323628","cover":"covers\/University.Tours.1600x900.jpg","slug":"campus-tours-2016-09-21-1200pm"},{"id":28,"title":"Conversation Corner: Mature Students And Student Parents","description":"","event_cover":null,"category_id":null,"creator_id":null,"created_at":"2016-09-05 23:18:25","updated_at":"2016-09-05 23:18:25","deleted_at":null,"date_start":"2016-09-21","date_end":null,"time_start":"1:00pm","time_end":"2:30pm","price":"Free","location_address":"Students' Union","location_name":"Room 8, Students' Union","tickets_link":"","featured":0,"subtitle":"","society_id":null,"lat":"53.464363","lng":"-2.2323628","cover":"covers\/CC16.Weblistings.Mature.16x9.jpg","slug":"conversation-corner-mature-students-and-student-parents-2016-09-21-100pm"},{"id":29,"title":"Film At 5: Eddie The Eagle","description":"","event_cover":null,"category_id":null,"creator_id":null,"created_at":"2016-09-05 23:18:25","updated_at":"2016-09-05 23:18:26","deleted_at":null,"date_start":"2016-09-21","date_end":null,"time_start":"5:00pm","time_end":"until finished","price":"Free","location_address":"Manchester Academy","location_name":"Academy 3, Students' Union","tickets_link":"","featured":0,"subtitle":"","society_id":null,"lat":"53.4635701","lng":"-2.2315516","cover":"covers\/Eddie.Eagle.1600x900.jpg","slug":"film-at-5-eddie-the-eagle-2016-09-21-500pm"},{"id":30,"title":"Film At 5: Star Wars Episode VII - The Force Awakens","description":"","event_cover":null,"category_id":null,"creator_id":null,"created_at":"2016-09-05 23:18:26","updated_at":"2016-09-05 23:18:27","deleted_at":null,"date_start":"2016-09-21","date_end":null,"time_start":"5:00pm","time_end":"until finished","price":"Free","location_address":"Renold Building","location_name":"Renold Building, C16","tickets_link":"","featured":0,"subtitle":"","society_id":null,"lat":"53.4748552","lng":"-2.2336139","cover":"covers\/Force.Awakens.1600x900.jpg","slug":"film-at-5-star-wars-episode-vii-the-force-awakens-2016-09-21-500pm"},{"id":31,"title":"Conversation Corner: Women Students","description":"","event_cover":null,"category_id":null,"creator_id":null,"created_at":"2016-09-05 23:18:27","updated_at":"2016-09-05 23:18:27","deleted_at":null,"date_start":"2016-09-21","date_end":null,"time_start":"5:00pm","time_end":"6:30pm","price":"Free","location_address":"Students' Union","location_name":"Council Chambers. Students' Union","tickets_link":"","featured":0,"subtitle":"","society_id":null,"lat":"53.464363","lng":"-2.2323628","cover":"covers\/CC16.Weblistings.Women.16x9.jpg","slug":"conversation-corner-women-students-2016-09-21-500pm"},{"id":32,"title":"Home Away From Home","description":"","event_cover":null,"category_id":null,"creator_id":null,"created_at":"2016-09-05 23:18:27","updated_at":"2016-09-05 23:18:28","deleted_at":null,"date_start":"2016-09-22","date_end":null,"time_start":"8:00am","time_end":"12:30pm","price":"Free","location_address":"Students' Union","location_name":"Room 8 ,Students' Union","tickets_link":"","featured":0,"subtitle":"","society_id":null,"lat":"53.464363","lng":"-2.2323628","cover":"covers\/Home.Away.From.Home.1600x900.jpg","slug":"home-away-from-home-2016-09-22-800am"},{"id":33,"title":"Home Away From Home","description":"","event_cover":null,"category_id":null,"creator_id":null,"created_at":"2016-09-05 23:18:28","updated_at":"2016-09-05 23:18:28","deleted_at":null,"date_start":"2016-09-22","date_end":null,"time_start":"2:30pm","time_end":"4:30pm","price":"Free","location_address":"Students' Union","location_name":"Room 8 ,Students' Union","tickets_link":"","featured":0,"subtitle":"","society_id":null,"lat":"53.464363","lng":"-2.2323628","cover":"covers\/Home.Away.From.Home.1600x900.jpg","slug":"home-away-from-home-2016-09-22-230pm"},{"id":34,"title":"Sports And Physical Activities Fair","description":"","event_cover":null,"category_id":null,"creator_id":null,"created_at":"2016-09-05 23:18:29","updated_at":"2016-09-05 23:18:29","deleted_at":null,"date_start":"2016-09-22","date_end":null,"time_start":"10:00am","time_end":"4:00pm","price":"Free","location_address":"Manchester Academy","location_name":"Manchester Academy","tickets_link":"","featured":0,"subtitle":"","society_id":null,"lat":"53.4635701","lng":"-2.2315516","cover":"covers\/S&PA16.Weblisting.16x9.jpg","slug":"sports-and-physical-activities-fair-2016-09-22-1000am"},{"id":35,"title":"Northern Quarter Caf\u00e9 Crawl","description":"","event_cover":null,"category_id":null,"creator_id":null,"created_at":"2016-09-05 23:18:29","updated_at":"2016-09-05 23:18:30","deleted_at":null,"date_start":"2016-09-22","date_end":null,"time_start":"11:00am","time_end":"until finished","price":"Free","location_address":"Students' Union","location_name":"Students' Union foyer","tickets_link":"","featured":0,"subtitle":"","society_id":null,"lat":"53.464363","lng":"-2.2323628","cover":"covers\/Cafe.Crawl.1600x900.jpg","slug":"northern-quarter-cafe-crawl-2016-09-22-1100am"},{"id":36,"title":"Campus Tours","description":"","event_cover":null,"category_id":null,"creator_id":null,"created_at":"2016-09-05 23:18:30","updated_at":"2016-09-05 23:18:30","deleted_at":null,"date_start":"2016-09-22","date_end":null,"time_start":"12:00pm","time_end":"3:00pm","price":"Free","location_address":"Students' Union","location_name":"Students' Union foyer","tickets_link":"","featured":0,"subtitle":"","society_id":null,"lat":"53.464363","lng":"-2.2323628","cover":"covers\/University.Tours.1600x900.jpg","slug":"campus-tours-2016-09-22-1200pm"},{"id":37,"title":"Talking 'bout My Education","description":"","event_cover":null,"category_id":null,"creator_id":null,"created_at":"2016-09-05 23:18:30","updated_at":"2016-09-05 23:18:31","deleted_at":null,"date_start":"2016-09-22","date_end":null,"time_start":"12:30pm","time_end":"2:30pm","price":"Free","location_address":"Students' Union","location_name":"Room 2, Students' Union","tickets_link":"","featured":0,"subtitle":"","society_id":null,"lat":"53.464363","lng":"-2.2323628","cover":"covers\/talkin_bout_my_education.jpg","slug":"talking-bout-my-education-2016-09-22-1230pm"},{"id":38,"title":"Conversation Corner: Students With Disabilities","description":"","event_cover":null,"category_id":null,"creator_id":null,"created_at":"2016-09-05 23:18:31","updated_at":"2016-09-05 23:18:32","deleted_at":null,"date_start":"2016-09-22","date_end":null,"time_start":"1:00pm","time_end":"2:30pm","price":"Free","location_address":"Students' Union","location_name":"Room 8, Students' Union","tickets_link":"","featured":0,"subtitle":"","society_id":null,"lat":"53.464363","lng":"-2.2323628","cover":"covers\/CC16.Weblistings.Dis.16x9.jpg","slug":"conversation-corner-students-with-disabilities-2016-09-22-100pm"},{"id":39,"title":"Conversation Corner: Postgraduate Students","description":"","event_cover":null,"category_id":null,"creator_id":null,"created_at":"2016-09-05 23:18:32","updated_at":"2016-09-05 23:18:32","deleted_at":null,"date_start":"2016-09-22","date_end":null,"time_start":"5:00pm","time_end":"6:30pm","price":"Free","location_address":"Students' Union","location_name":"Room 8, Students' Union","tickets_link":"","featured":0,"subtitle":"","society_id":null,"lat":"53.464363","lng":"-2.2323628","cover":"covers\/CC16.Weblistings.Post.16x9.jpg","slug":"conversation-corner-postgraduate-students-2016-09-22-500pm"},{"id":40,"title":"Film At 5: The Imitation Game","description":"","event_cover":null,"category_id":null,"creator_id":null,"created_at":"2016-09-05 23:18:32","updated_at":"2016-09-05 23:18:33","deleted_at":null,"date_start":"2016-09-22","date_end":null,"time_start":"5:00pm","time_end":"until finished","price":"Free","location_address":"Students' Union","location_name":"Council Chambers, Students' Union (68)","tickets_link":"","featured":0,"subtitle":"","society_id":null,"lat":"53.464363","lng":"-2.2323628","cover":"covers\/Imitation.Game.1600x900.jpg","slug":"film-at-5-the-imitation-game-2016-09-22-500pm"},{"id":41,"title":"Outdoor Food Market","description":"","event_cover":null,"category_id":null,"creator_id":null,"created_at":"2016-09-05 23:18:33","updated_at":"2016-09-05 23:18:34","deleted_at":null,"date_start":"2016-09-23","date_end":null,"time_start":"10:00am","time_end":"4:00pm","price":"Free","location_address":"Students' Union","location_name":"Marquee next to Students' Union","tickets_link":"","featured":0,"subtitle":"","society_id":null,"lat":"53.464363","lng":"-2.2323628","cover":"covers\/Outdoor.Food.Market.1600x900.jpg","slug":"outdoor-food-market-2016-09-23-1000am"},{"id":42,"title":"Grub Club","description":"","event_cover":null,"category_id":null,"creator_id":null,"created_at":"2016-09-05 23:18:34","updated_at":"2016-09-05 23:18:34","deleted_at":null,"date_start":"2016-09-23","date_end":null,"time_start":"12:00pm","time_end":"until finished","price":"Free","location_address":"Students' Union","location_name":"Marquee next to Students' Union","tickets_link":"","featured":0,"subtitle":"","society_id":null,"lat":"53.464363","lng":"-2.2323628","cover":"covers\/Grub.Club.1600x900.jpg","slug":"grub-club-2016-09-23-1200pm"},{"id":43,"title":"Grub Club","description":"","event_cover":null,"category_id":null,"creator_id":null,"created_at":"2016-09-05 23:18:34","updated_at":"2016-09-05 23:18:35","deleted_at":null,"date_start":"2016-09-23","date_end":null,"time_start":"1:30pm","time_end":"until finished","price":"Free","location_address":"Students' Union","location_name":"Marquee next to Students' Union","tickets_link":"","featured":0,"subtitle":"","society_id":null,"lat":"53.464363","lng":"-2.2323628","cover":"covers\/Grub.Club.1600x900.jpg","slug":"grub-club-2016-09-23-130pm"},{"id":44,"title":"Grub Club","description":"","event_cover":null,"category_id":null,"creator_id":null,"created_at":"2016-09-05 23:18:35","updated_at":"2016-09-05 23:18:35","deleted_at":null,"date_start":"2016-09-23","date_end":null,"time_start":"3:00pm","time_end":"until finished","price":"Free","location_address":"Students' Union","location_name":"Marquee next to Students' Union","tickets_link":"","featured":0,"subtitle":"","society_id":null,"lat":"53.464363","lng":"-2.2323628","cover":"covers\/Grub.Club.1600x900.jpg","slug":"grub-club-2016-09-23-300pm"},{"id":45,"title":"Campus Tours","description":"","event_cover":null,"category_id":null,"creator_id":null,"created_at":"2016-09-05 23:18:35","updated_at":"2016-09-05 23:18:36","deleted_at":null,"date_start":"2016-09-23","date_end":null,"time_start":"12:00pm","time_end":"3:00pm","price":"Free","location_address":"Students' Union","location_name":"Students' Union foyer","tickets_link":"","featured":0,"subtitle":"","society_id":null,"lat":"53.464363","lng":"-2.2323628","cover":"covers\/University.Tours.1600x900.jpg","slug":"campus-tours-2016-09-23-1200pm"},{"id":46,"title":"Film At Five: The Lego Movie","description":"","event_cover":null,"category_id":null,"creator_id":null,"created_at":"2016-09-05 23:18:36","updated_at":"2016-09-05 23:18:36","deleted_at":null,"date_start":"2016-09-23","date_end":null,"time_start":"5:00pm","time_end":"until finished","price":"Free","location_address":"Students' Union","location_name":"Council Chambers, Students' Union","tickets_link":"","featured":0,"subtitle":"","society_id":null,"lat":"53.464363","lng":"-2.2323628","cover":"covers\/Lego.Movie.1600x900.jpg","slug":"film-at-five-the-lego-movie-2016-09-23-500pm"},{"id":47,"title":"The Union Bar Weekend Warm Up","description":"","event_cover":null,"category_id":null,"creator_id":null,"created_at":"2016-09-05 23:18:37","updated_at":"2016-09-05 23:18:37","deleted_at":null,"date_start":"2016-09-23","date_end":null,"time_start":"7:00pm","time_end":"3:00am","price":"Free","location_address":"Students' Union","location_name":"Union Bar, Students' Union","tickets_link":"","featured":0,"subtitle":"","society_id":null,"lat":"53.464363","lng":"-2.2323628","cover":"covers\/Union.Bar.1600x900.jpg","slug":"the-union-bar-weekend-warm-up-2016-09-23-700pm"},{"id":48,"title":"Pangaea","description":"Pangaea Festival returns this September! Join over 6,000 fellow students Down the Rabbit Hole, as we unlock a world of fantasy, puzzle and splendid mystery. Prepare yourself for the descent downwards into the parallel universe of Pangaea, dress for the occasion and you\u2019ll never want to leave this wonderland. http:\/\/pangaeafestival.co.uk\/","event_cover":null,"category_id":null,"creator_id":null,"created_at":"2016-09-05 23:18:37","updated_at":"2016-09-05 23:18:38","deleted_at":null,"date_start":"2016-09-24","date_end":null,"time_start":"8:00pm","time_end":"5:00am","price":"Wristband","location_address":"Students' Union","location_name":"Students' Union","tickets_link":"https:\/\/www.ticketline.co.uk\/order\/tickets\/13319083","featured":1,"subtitle":"","society_id":null,"lat":"53.464363","lng":"-2.2323628","cover":"covers\/PanSep16.WristbandAd.1600x900-01.jpg","slug":"pangaea-2016-09-24-800pm"},{"id":49,"title":"Manchester Academy \/ Albert Hall","description":"Grey wristbands will be attending Manchester Academy: Carnival Magnifico presents Tough Love. Cream wristbands will be attending The Albert Hall: Bipolar Sunshine at The Albert Hall with Juicy \/ Gold Teeth \/ Murkage DJs","event_cover":null,"category_id":null,"creator_id":null,"created_at":"2016-09-05 23:18:38","updated_at":"2016-09-05 23:18:38","deleted_at":null,"date_start":"2016-09-22","date_end":null,"time_start":"8:00pm","time_end":"5:00am","price":"Wristband","location_address":"Manchester Academy","location_name":"Manchester Academy \/ Albert Hall","tickets_link":"https:\/\/www.ticketline.co.uk\/order\/tickets\/13319083","featured":1,"subtitle":"","society_id":null,"lat":"53.4635701","lng":"-2.2315516","cover":"covers\/Albert.hall.1600x900.jpg","slug":"manchester-academy-albert-hall-2016-09-22-800pm"},{"id":50,"title":"Carnival Magnifico","description":"Cream wristbands will be attending Manchester Academy: Carnival Magnifico presents Tough Love. Grey wristbands will be attending The Albert Hall: Bipolar Sunshine at The Albert Hall with Juicy \/ Gold Teeth \/ Murkage DJs","event_cover":null,"category_id":null,"creator_id":null,"created_at":"2016-09-05 23:18:38","updated_at":"2016-09-05 23:18:39","deleted_at":null,"date_start":"2016-09-20","date_end":null,"time_start":"8:00pm","time_end":"5:00am","price":"Wristband","location_address":"Manchester Academy","location_name":"Manchester Academy \/ Albert Hall","tickets_link":"https:\/\/www.ticketline.co.uk\/order\/tickets\/13319083","featured":1,"subtitle":"","society_id":null,"lat":"53.4635701","lng":"-2.2315516","cover":"covers\/Carnival Magnifico16x9-01.jpg","slug":"carnival-magnifico-2016-09-20-800pm"},{"id":51,"title":"Deansgate Locks","description":"Comedy Store, hosted by Pop Bubble Rock \u2014 Ark, hosted by Brooks \u2014 Revolution, hosted by Propbox and Covert \u2014 Lola Lo, hosted by Cherry \u2014 Bar Bah, hosted by Remake Remodel.","event_cover":null,"category_id":null,"creator_id":null,"created_at":"2016-09-05 23:18:39","updated_at":"2016-09-05 23:18:40","deleted_at":null,"date_start":"2016-09-18","date_end":null,"time_start":"8:00pm","time_end":"5:00am","price":"Wristband","location_address":"Deansgate Locks","location_name":"Deansgate Locks","tickets_link":"https:\/\/www.ticketline.co.uk\/order\/tickets\/13319083","featured":1,"subtitle":"","society_id":null,"lat":"53.48095","lng":"-2.23743","cover":"covers\/wristband3.jpg","slug":"deansgate-locks-2016-09-18-800pm"},{"id":52,"title":"Postgraduate Pizza Evening","description":"","event_cover":null,"category_id":null,"creator_id":null,"created_at":"2016-09-05 23:18:40","updated_at":"2016-09-05 23:18:40","deleted_at":null,"date_start":"2016-09-24","date_end":null,"time_start":"6:00pm","time_end":"8:00pm","price":"Free","location_address":"Manchester Academy","location_name":"Academy 2, Students' Union","tickets_link":"","featured":0,"subtitle":"","society_id":null,"lat":"53.4635701","lng":"-2.2315516","cover":"covers\/Postgrad.Pizza.1600x900.jpg","slug":"postgraduate-pizza-evening-2016-09-24-600pm"},{"id":53,"title":"Living At Home Students Speed Meet","description":"","event_cover":null,"category_id":null,"creator_id":null,"created_at":"2016-09-05 23:18:40","updated_at":"2016-09-05 23:18:41","deleted_at":null,"date_start":"2016-09-22","date_end":null,"time_start":"2:00pm","time_end":"3:30pm","price":"Free","location_address":"Students' Union","location_name":"Council Chambers, Students' Union","tickets_link":"","featured":0,"subtitle":"","society_id":null,"lat":"53.464363","lng":"-2.2323628","cover":"covers\/Living.At.Home.1600x900.jpg","slug":"living-at-home-students-speed-meet-2016-09-22-200pm"},{"id":54,"title":"Volunteering Showcase","description":"Activities:<ul><li>Take part in micro-volunteering that will support our work in the local community<\/li><li>Sign-up to one-off volunteering opportunities with children and adults<\/li><li>Have a go at quizzes and get to know the issues we tackle in Manchester<\/li><\/ul>","event_cover":null,"category_id":null,"creator_id":null,"created_at":"2016-09-05 23:18:41","updated_at":"2016-09-05 23:18:41","deleted_at":null,"date_start":"2016-09-21","date_end":null,"time_start":"12:00pm","time_end":"1:30pm","price":"Free","location_address":"Students' Union","location_name":"Council Chambers, 2nd floor, Students' Union","tickets_link":"","featured":0,"subtitle":"","society_id":null,"lat":"53.464363","lng":"-2.2323628","cover":"","slug":"volunteering-showcase-2016-09-21-1200pm"}]